tradingfeatures/__init__.py
tradingfeatures/api_base.py
tradingfeatures/configs.py
tradingfeatures/google_trends.py
tradingfeatures/uber.py
tradingfeatures/apis/__init__.py
tradingfeatures/apis/binance/__init__.py
tradingfeatures/apis/binance/base.py
tradingfeatures/apis/binance/funding.py
tradingfeatures/apis/binance/main.py
tradingfeatures/apis/binance/order_book.py
tradingfeatures/apis/bitfinex/__init__.py
tradingfeatures/apis/bitfinex/base.py
tradingfeatures/apis/bitfinex/main.py
tradingfeatures/apis/bitfinex/shortlong.py
tradingfeatures/apis/bitmex/__init__.py
tradingfeatures/apis/bitmex/base.py
tradingfeatures/apis/bitmex/funding.py
tradingfeatures/apis/bitmex/main.py
tradingfeatures/apis/bitmex/quote.py
tradingfeatures/apis/bitstamp/__init__.py
tradingfeatures/apis/bitstamp/base.py
tradingfeatures/apis/bitstamp/main.py
tradingfeatures-0.8.0.dist-info/LICENSE
tradingfeatures-0.8.0.dist-info/METADATA
tradingfeatures-0.8.0.dist-info/WHEEL
tradingfeatures-0.8.0.dist-info/top_level.txt
tradingfeatures-0.8.0.dist-info/RECORD
