Metadata-Version: 2.1
Name: tradingfeatures
Version: 0.8.0
Summary: A useful tool to download market history from popular exchanges.
Author-email: Onur Cetinkol <realiti44@gmail.com>
License: MIT License
Keywords: download,market,history,binance,bitfinex,bitmex,bitstamp
Classifier: Programming Language :: Python :: 3
Classifier: License :: OSI Approved :: MIT License
Classifier: Operating System :: OS Independent
Requires-Python: >=3.11
License-File: LICENSE
Requires-Dist: numpy
Requires-Dist: pandas
Requires-Dist: requests
Requires-Dist: tqdm
